{"measurement 5":{"ap23":{"capabilities":"[ESS]","level":-87,"frequency":2462,"BSSID":"00:27:0d:2e:f2:81","SSID":"aalto open"},"ap14":{"capabilities":"[WPA2-PSK-CCMP][ESS]","level":-77,"frequency":2437,"BSSID":"00:24:36:a6:e0:13","SSID":"marjonverkko"},"ap24":{"capabilities":"[ESS]","level":-87,"frequency":2437,"BSSID":"00:27:0d:2d:d0:71","SSID":"aalto open"},"ap15":{"capabilities":"[WPA2-EAP-CCMP][ESS]","level":-77,"frequency":2437,"BSSID":"00:27:0d:2d:d0:72","SSID":"eduroam"},"ap12":{"capabilities":"[ESS]","level":-80,"frequency":5320,"BSSID":"08:1f:f3:b2:d0:ae","SSID":"aalto open"},"ap13":{"capabilities":"[WPA2-EAP-CCMP][ESS]","level":-80,"frequency":5220,"BSSID":"00:27:0d:2e:79:fd","SSID":"eduroam"},"ap18":{"capabilities":"[WPA2-PSK-CCMP][ESS]","level":-93,"frequency":5540,"BSSID":"00:24:36:a6:e0:14","SSID":"marjonverkko"},"ap19":{"capabilities":"[WPA2-EAP-CCMP][ESS]","level":-89,"frequency":2462,"BSSID":"00:27:0d:08:c2:12","SSID":"eduroam"},"ap16":{"capabilities":"[WPA2-PSK-CCMP][ESS]","level":-81,"frequency":2467,"BSSID":"30:85:a9:6c:9b:e2","SSID":"Ren_2.4G"},"ap17":{"capabilities":"[WPA2-EAP-CCMP][ESS]","level":-93,"frequency":5200,"BSSID":"00:27:0d:2e:f2:8d","SSID":"eduroam"},"ap9":{"capabilities":"[ESS]","level":-90,"frequency":2437,"BSSID":"00:27:0d:30:2a:61","SSID":"aalto open"},"ap8":{"capabilities":"[ESS]","level":-59,"frequency":2412,"BSSID":"24:01:c7:77:f4:71","SSID":"aalto open"},"ap7":{"capabilities":"[WPA-PSK-TKIP+CCMP][WPA2-PSK-CCMP][ESS]","level":-69,"frequency":2437,"BSSID":"c8:d3:a3:0e:cd:cc","SSID":"eMulTestBed"},"ap20":{"capabilities":"[ESS]","level":-76,"frequency":5200,"BSSID":"24:01:c7:77:f4:7e","SSID":"aalto open"},"ap11":{"capabilities":"[ESS]","level":-73,"frequency":5600,"BSSID":"d4:ca:6d:ff:31:87","SSID":"NETLEAP"},"ap10":{"capabilities":"[ESS]","level":-67,"frequency":2412,"BSSID":"00:27:0d:2e:79:f1","SSID":"aalto open"},"ap22":{"capabilities":"[ESS]","level":-82,"frequency":2462,"BSSID":"00:27:0d:08:c2:11","SSID":"aalto open"},"ap21":{"capabilities":"[ESS]","level":-80,"frequency":5220,"BSSID":"00:27:0d:2e:79:fe","SSID":"aalto open"},"ap2":{"capabilities":"[WPA2-EAP-CCMP][ESS]","level":-61,"frequency":2412,"BSSID":"24:01:c7:77:f4:72","SSID":"eduroam"},"ap1":{"capabilities":"[WPA2-EAP-CCMP][ESS]","level":-90,"frequency":2437,"BSSID":"00:27:0d:30:2a:62","SSID":"eduroam"},"ap6":{"capabilities":"[WPA2-EAP-CCMP][ESS]","level":-80,"frequency":5320,"BSSID":"08:1f:f3:b2:d0:ad","SSID":"eduroam"},"ap5":{"capabilities":"[WPA2-EAP-CCMP][ESS]","level":-76,"frequency":5200,"BSSID":"24:01:c7:77:f4:7d","SSID":"eduroam"},"ap4":{"capabilities":"[WPA2-EAP-CCMP][ESS]","level":-75,"frequency":5200,"BSSID":"24:01:c7:77:f4:7f","SSID":"aalto"},"ap3":{"capabilities":"[WPA2-EAP-CCMP][ESS]","level":-67,"frequency":2412,"BSSID":"00:27:0d:2e:79:f2","SSID":"eduroam"}},"measurement 4":{"ap14":{"capabilities":"[WPA2-EAP-CCMP][ESS]","level":-84,"frequency":5240,"BSSID":"00:27:0d:30:2a:6f","SSID":"aalto"},"ap15":{"capabilities":"[WPA2-EAP-CCMP][ESS]","level":-80,"frequency":2412,"BSSID":"a4:56:30:e8:17:60","SSID":"aalto"},"ap12":{"capabilities":"[WPA2-EAP-CCMP][ESS]","level":-79,"frequency":2412,"BSSID":"24:01:c7:b8:d4:e2","SSID":"eduroam"},"ap13":{"capabilities":"[WPA2-EAP-CCMP][ESS]","level":-84,"frequency":5320,"BSSID":"08:1f:f3:b2:d0:af","SSID":"aalto"},"ap18":{"capabilities":"[WPA2-EAP-CCMP][ESS]","level":-83,"frequency":2412,"BSSID":"00:27:0d:08:bc:52","SSID":"eduroam"},"ap19":{"capabilities":"[WPA2-EAP-CCMP][ESS]","level":-85,"frequency":2462,"BSSID":"08:1f:f3:b2:d0:a2","SSID":"eduroam"},"ap34":{"capabilities":"[ESS]","level":-88,"frequency":5220,"BSSID":"00:27:0d:2d:dd:ce","SSID":"aalto open"},"ap16":{"capabilities":"[WPA2-EAP-CCMP][ESS]","level":-80,"frequency":2462,"BSSID":"00:27:0d:0b:d1:c2","SSID":"eduroam"},"ap35":{"capabilities":"[ESS]","level":-91,"frequency":2437,"BSSID":"a0:cf:5b:fa:34:e1","SSID":"aalto open"},"ap17":{"capabilities":"[WPA2-PSK-CCMP][ESS]","level":-82,"frequency":2437,"BSSID":"26:f7:e4:31:c2:c1","SSID":"iPhone"},"ap33":{"capabilities":"[ESS]","level":-88,"frequency":5240,"BSSID":"00:27:0d:30:2a:6e","SSID":"aalto open"},"ap32":{"capabilities":"[ESS]","level":-85,"frequency":5320,"BSSID":"08:1f:f3:b2:d0:ae","SSID":"aalto open"},"ap9":{"capabilities":"[WPA2-EAP-CCMP][ESS]","level":-81,"frequency":5200,"BSSID":"24:01:c7:77:f4:7d","SSID":"eduroam"},"ap31":{"capabilities":"[ESS]","level":-78,"frequency":2412,"BSSID":"24:01:c7:b8:d4:e1","SSID":"aalto open"},"ap8":{"capabilities":"[WPA2-EAP-CCMP][ESS]","level":-81,"frequency":5200,"BSSID":"24:01:c7:77:f4:7f","SSID":"aalto"},"ap30":{"capabilities":"[ESS]","level":-81,"frequency":5600,"BSSID":"d4:ca:6d:ff:31:87","SSID":"NETLEAP"},"ap7":{"capabilities":"[WPA2-EAP-CCMP][ESS]","level":-73,"frequency":2412,"BSSID":"00:27:0d:2e:79:f2","SSID":"eduroam"},"ap11":{"capabilities":"[WPA2-EAP-CCMP][ESS]","level":-83,"frequency":5320,"BSSID":"08:1f:f3:b2:d0:ad","SSID":"eduroam"},"ap10":{"capabilities":"[WPA2-PSK-CCMP][ESS]","level":-78,"frequency":2462,"BSSID":"a0:21:b7:9d:55:e9","SSID":"OpenWrt"},"ap2":{"capabilities":"[WPA2-EAP-CCMP][ESS]","level":-69,"frequency":2462,"BSSID":"08:1f:f3:b2:d4:b2","SSID":"eduroam"},"ap1":{"capabilities":"[WPA2-EAP-CCMP][ESS]","level":-68,"frequency":2462,"BSSID":"08:1f:f3:b2:d4:b0","SSID":"aalto"},"ap6":{"capabilities":"[WPA2-EAP-CCMP][ESS]","level":-68,"frequency":2412,"BSSID":"24:01:c7:77:f4:72","SSID":"eduroam"},"ap5":{"capabilities":"[WPA2-EAP-CCMP][ESS]","level":-66,"frequency":2437,"BSSID":"00:27:0d:30:2a:60","SSID":"aalto"},"ap4":{"capabilities":"[WPA2-EAP-CCMP][ESS]","level":-66,"frequency":2412,"BSSID":"24:01:c7:77:f4:70","SSID":"aalto"},"ap3":{"capabilities":"[WPA2-EAP-CCMP][ESS]","level":-61,"frequency":2437,"BSSID":"00:27:0d:30:2a:62","SSID":"eduroam"},"ap23":{"capabilities":"[WPA2-EAP-CCMP][ESS]","level":-89,"frequency":2412,"BSSID":"00:27:0d:08:be:82","SSID":"eduroam"},"ap24":{"capabilities":"[WPA2-EAP-CCMP][ESS]","level":-90,"frequency":2412,"BSSID":"08:1f:f3:e0:1a:40","SSID":"aalto"},"ap25":{"capabilities":"[WPA2-EAP-CCMP][ESS]","level":-90,"frequency":2412,"BSSID":"f4:4e:05:78:40:20","SSID":"aalto"},"ap26":{"capabilities":"[ESS]","level":-57,"frequency":2412,"BSSID":"24:01:c7:77:f4:71","SSID":"aalto open"},"ap27":{"capabilities":"[ESS]","level":-61,"frequency":2437,"BSSID":"00:27:0d:30:2a:61","SSID":"aalto open"},"ap28":{"capabilities":"[ESS]","level":-69,"frequency":2462,"BSSID":"08:1f:f3:b2:d4:b1","SSID":"aalto open"},"ap29":{"capabilities":"[ESS]","level":-73,"frequency":2412,"BSSID":"00:27:0d:2e:79:f1","SSID":"aalto open"},"ap20":{"capabilities":"[WPA2-EAP-CCMP][ESS]","level":-91,"frequency":5220,"BSSID":"00:27:0d:2d:dd:cd","SSID":"eduroam"},"ap22":{"capabilities":"[WPA-PSK-TKIP+CCMP][WPA2-PSK-CCMP][ESS]","level":-88,"frequency":2437,"BSSID":"c8:d3:a3:0e:cd:cc","SSID":"eMulTestBed"},"ap21":{"capabilities":"[WPA2-EAP-CCMP][ESS]","level":-87,"frequency":2437,"BSSID":"a0:cf:5b:fa:34:e0","SSID":"aalto"}},"measurement 7":{"ap14":{"capabilities":"[ESS]","level":-79,"frequency":5220,"BSSID":"00:27:0d:2e:79:fe","SSID":"aalto open"},"ap15":{"capabilities":"[ESS]","level":-73,"frequency":2437,"BSSID":"00:27:0d:2d:d0:71","SSID":"aalto open"},"ap12":{"capabilities":"[WPA2-PSK-CCMP][ESS]","level":-84,"frequency":2467,"BSSID":"30:85:a9:6c:9b:e2","SSID":"Ren_2.4G"},"ap13":{"capabilities":"[ESS]","level":-77,"frequency":5200,"BSSID":"24:01:c7:77:f4:7e","SSID":"aalto open"},"ap18":{"capabilities":"[WPA2-EAP-CCMP][ESS]","level":-82,"frequency":5220,"BSSID":"00:27:0d:2e:79:ff","SSID":"aalto"},"ap19":{"capabilities":"[WPA2-EAP-CCMP][ESS]","level":-88,"frequency":5320,"BSSID":"08:1f:f3:b2:d0:af","SSID":"aalto"},"ap16":{"capabilities":"[WPA2-EAP-CCMP][ESS]","level":-58,"frequency":2412,"BSSID":"24:01:c7:77:f4:70","SSID":"aalto"},"ap17":{"capabilities":"[WPA2-EAP-CCMP][ESS]","level":-77,"frequency":2437,"BSSID":"00:27:0d:2d:d0:70","SSID":"aalto"},"ap9":{"capabilities":"[ESS]","level":-87,"frequency":5320,"BSSID":"08:1f:f3:b2:d0:ae","SSID":"aalto open"},"ap8":{"capabilities":"[ESS]","level":-72,"frequency":5600,"BSSID":"d4:ca:6d:ff:31:87","SSID":"NETLEAP"},"ap7":{"capabilities":"[ESS]","level":-70,"frequency":2412,"BSSID":"00:27:0d:2e:79:f1","SSID":"aalto open"},"ap20":{"capabilities":"[WPA2-EAP-CCMP][ESS]","level":-86,"frequency":2462,"BSSID":"00:27:0d:2e:f2:82","SSID":"eduroam"},"ap11":{"capabilities":"[WPA2-PSK-CCMP][ESS]","level":-77,"frequency":2437,"BSSID":"00:24:36:a6:e0:13","SSID":"marjonverkko"},"ap10":{"capabilities":"[WPA2-EAP-CCMP][ESS]","level":-78,"frequency":5220,"BSSID":"00:27:0d:2e:79:fd","SSID":"eduroam"},"ap21":{"capabilities":"[ESS]","level":-75,"frequency":2462,"BSSID":"08:1f:f3:b2:d0:a1","SSID":"aalto open"},"ap2":{"capabilities":"[WPA2-EAP-CCMP][ESS]","level":-77,"frequency":5200,"BSSID":"24:01:c7:77:f4:7f","SSID":"aalto"},"ap1":{"capabilities":"[WPA2-EAP-CCMP][ESS]","level":-62,"frequency":2412,"BSSID":"24:01:c7:77:f4:72","SSID":"eduroam"},"ap6":{"capabilities":"[ESS]","level":-59,"frequency":2412,"BSSID":"24:01:c7:77:f4:71","SSID":"aalto open"},"ap5":{"capabilities":"[WPA-PSK-TKIP+CCMP][WPA2-PSK-CCMP][ESS]","level":-68,"frequency":2437,"BSSID":"c8:d3:a3:0e:cd:cc","SSID":"eMulTestBed"},"ap4":{"capabilities":"[WPA2-EAP-CCMP][ESS]","level":-89,"frequency":5320,"BSSID":"08:1f:f3:b2:d0:ad","SSID":"eduroam"},"ap3":{"capabilities":"[WPA2-EAP-CCMP][ESS]","level":-79,"frequency":5200,"BSSID":"24:01:c7:77:f4:7d","SSID":"eduroam"}},"measurement 6":{"ap14":{"capabilities":"[ESS]","level":-79,"frequency":5220,"BSSID":"00:27:0d:2e:79:fe","SSID":"aalto open"},"ap15":{"capabilities":"[ESS]","level":-73,"frequency":2437,"BSSID":"00:27:0d:2d:d0:71","SSID":"aalto open"},"ap12":{"capabilities":"[WPA2-PSK-CCMP][ESS]","level":-84,"frequency":2467,"BSSID":"30:85:a9:6c:9b:e2","SSID":"Ren_2.4G"},"ap13":{"capabilities":"[ESS]","level":-77,"frequency":5200,"BSSID":"24:01:c7:77:f4:7e","SSID":"aalto open"},"ap18":{"capabilities":"[WPA2-EAP-CCMP][ESS]","level":-82,"frequency":5220,"BSSID":"00:27:0d:2e:79:ff","SSID":"aalto"},"ap19":{"capabilities":"[WPA2-EAP-CCMP][ESS]","level":-88,"frequency":5320,"BSSID":"08:1f:f3:b2:d0:af","SSID":"aalto"},"ap16":{"capabilities":"[WPA2-EAP-CCMP][ESS]","level":-58,"frequency":2412,"BSSID":"24:01:c7:77:f4:70","SSID":"aalto"},"ap17":{"capabilities":"[WPA2-EAP-CCMP][ESS]","level":-77,"frequency":2437,"BSSID":"00:27:0d:2d:d0:70","SSID":"aalto"},"ap9":{"capabilities":"[ESS]","level":-87,"frequency":5320,"BSSID":"08:1f:f3:b2:d0:ae","SSID":"aalto open"},"ap8":{"capabilities":"[ESS]","level":-72,"frequency":5600,"BSSID":"d4:ca:6d:ff:31:87","SSID":"NETLEAP"},"ap7":{"capabilities":"[ESS]","level":-70,"frequency":2412,"BSSID":"00:27:0d:2e:79:f1","SSID":"aalto open"},"ap20":{"capabilities":"[WPA2-EAP-CCMP][ESS]","level":-86,"frequency":2462,"BSSID":"00:27:0d:2e:f2:82","SSID":"eduroam"},"ap11":{"capabilities":"[WPA2-PSK-CCMP][ESS]","level":-77,"frequency":2437,"BSSID":"00:24:36:a6:e0:13","SSID":"marjonverkko"},"ap10":{"capabilities":"[WPA2-EAP-CCMP][ESS]","level":-78,"frequency":5220,"BSSID":"00:27:0d:2e:79:fd","SSID":"eduroam"},"ap21":{"capabilities":"[ESS]","level":-75,"frequency":2462,"BSSID":"08:1f:f3:b2:d0:a1","SSID":"aalto open"},"ap2":{"capabilities":"[WPA2-EAP-CCMP][ESS]","level":-77,"frequency":5200,"BSSID":"24:01:c7:77:f4:7f","SSID":"aalto"},"ap1":{"capabilities":"[WPA2-EAP-CCMP][ESS]","level":-62,"frequency":2412,"BSSID":"24:01:c7:77:f4:72","SSID":"eduroam"},"ap6":{"capabilities":"[ESS]","level":-59,"frequency":2412,"BSSID":"24:01:c7:77:f4:71","SSID":"aalto open"},"ap5":{"capabilities":"[WPA-PSK-TKIP+CCMP][WPA2-PSK-CCMP][ESS]","level":-68,"frequency":2437,"BSSID":"c8:d3:a3:0e:cd:cc","SSID":"eMulTestBed"},"ap4":{"capabilities":"[WPA2-EAP-CCMP][ESS]","level":-89,"frequency":5320,"BSSID":"08:1f:f3:b2:d0:ad","SSID":"eduroam"},"ap3":{"capabilities":"[WPA2-EAP-CCMP][ESS]","level":-79,"frequency":5200,"BSSID":"24:01:c7:77:f4:7d","SSID":"eduroam"}},"measurement 9":{"ap14":{"capabilities":"[WPA2-EAP-CCMP][ESS]","level":-84,"frequency":2462,"BSSID":"00:27:0d:2e:f2:82","SSID":"eduroam"},"ap15":{"capabilities":"[WPA2-EAP-CCMP][ESS]","level":-81,"frequency":2462,"BSSID":"08:1f:f3:b2:d0:a0","SSID":"aalto"},"ap12":{"capabilities":"[ESS]","level":-70,"frequency":5220,"BSSID":"00:27:0d:2e:79:fe","SSID":"aalto open"},"ap13":{"capabilities":"[WPA2-EAP-CCMP][ESS]","level":-68,"frequency":5220,"BSSID":"00:27:0d:2e:79:ff","SSID":"aalto"},"ap18":{"capabilities":"[WPA2-PSK-CCMP][ESS]","level":-94,"frequency":5540,"BSSID":"00:24:36:a6:e0:14","SSID":"marjonverkko"},"ap19":{"capabilities":"[ESS]","level":-91,"frequency":5180,"BSSID":"00:27:0d:08:c2:1e","SSID":"aalto open"},"ap16":{"capabilities":"[WPA2-EAP-CCMP][ESS]","level":-84,"frequency":2437,"BSSID":"00:27:0d:30:2a:62","SSID":"eduroam"},"ap17":{"capabilities":"[WPA2-EAP-CCMP][ESS]","level":-93,"frequency":5200,"BSSID":"00:27:0d:2e:f2:8d","SSID":"eduroam"},"ap9":{"capabilities":"[WPA2-EAP-CCMP][ESS]","level":-69,"frequency":5220,"BSSID":"00:27:0d:2e:79:fd","SSID":"eduroam"},"ap8":{"capabilities":"[ESS]","level":-82,"frequency":5320,"BSSID":"08:1f:f3:b2:d0:ae","SSID":"aalto open"},"ap7":{"capabilities":"[ESS]","level":-77,"frequency":5600,"BSSID":"d4:ca:6d:ff:31:87","SSID":"NETLEAP"},"ap11":{"capabilities":"[WPA2-PSK-CCMP][ESS]","level":-81,"frequency":2467,"BSSID":"30:85:a9:6c:9b:e2","SSID":"Ren_2.4G"},"ap10":{"capabilities":"[WPA2-PSK-CCMP][ESS]","level":-77,"frequency":2437,"BSSID":"00:24:36:a6:e0:13","SSID":"marjonverkko"},"ap2":{"capabilities":"[WPA2-EAP-CCMP][ESS]","level":-81,"frequency":5200,"BSSID":"24:01:c7:77:f4:7d","SSID":"eduroam"},"ap1":{"capabilities":"[WPA2-EAP-CCMP][ESS]","level":-67,"frequency":2412,"BSSID":"24:01:c7:77:f4:72","SSID":"eduroam"},"ap6":{"capabilities":"[ESS]","level":-63,"frequency":2412,"BSSID":"00:27:0d:2e:79:f1","SSID":"aalto open"},"ap5":{"capabilities":"[ESS]","level":-70,"frequency":2412,"BSSID":"24:01:c7:77:f4:71","SSID":"aalto open"},"ap4":{"capabilities":"[WPA-PSK-TKIP+CCMP][WPA2-PSK-CCMP][ESS]","level":-71,"frequency":2437,"BSSID":"c8:d3:a3:0e:cd:cc","SSID":"eMulTestBed"},"ap3":{"capabilities":"[WPA2-EAP-CCMP][ESS]","level":-81,"frequency":5320,"BSSID":"08:1f:f3:b2:d0:ad","SSID":"eduroam"}},"measurement 8":{"ap14":{"capabilities":"[WPA2-EAP-CCMP][ESS]","level":-84,"frequency":2462,"BSSID":"00:27:0d:2e:f2:82","SSID":"eduroam"},"ap15":{"capabilities":"[WPA2-EAP-CCMP][ESS]","level":-81,"frequency":2462,"BSSID":"08:1f:f3:b2:d0:a0","SSID":"aalto"},"ap12":{"capabilities":"[ESS]","level":-70,"frequency":5220,"BSSID":"00:27:0d:2e:79:fe","SSID":"aalto open"},"ap13":{"capabilities":"[WPA2-EAP-CCMP][ESS]","level":-68,"frequency":5220,"BSSID":"00:27:0d:2e:79:ff","SSID":"aalto"},"ap18":{"capabilities":"[WPA2-PSK-CCMP][ESS]","level":-94,"frequency":5540,"BSSID":"00:24:36:a6:e0:14","SSID":"marjonverkko"},"ap19":{"capabilities":"[ESS]","level":-91,"frequency":5180,"BSSID":"00:27:0d:08:c2:1e","SSID":"aalto open"},"ap16":{"capabilities":"[WPA2-EAP-CCMP][ESS]","level":-84,"frequency":2437,"BSSID":"00:27:0d:30:2a:62","SSID":"eduroam"},"ap17":{"capabilities":"[WPA2-EAP-CCMP][ESS]","level":-93,"frequency":5200,"BSSID":"00:27:0d:2e:f2:8d","SSID":"eduroam"},"ap9":{"capabilities":"[WPA2-EAP-CCMP][ESS]","level":-69,"frequency":5220,"BSSID":"00:27:0d:2e:79:fd","SSID":"eduroam"},"ap8":{"capabilities":"[ESS]","level":-82,"frequency":5320,"BSSID":"08:1f:f3:b2:d0:ae","SSID":"aalto open"},"ap7":{"capabilities":"[ESS]","level":-77,"frequency":5600,"BSSID":"d4:ca:6d:ff:31:87","SSID":"NETLEAP"},"ap11":{"capabilities":"[WPA2-PSK-CCMP][ESS]","level":-81,"frequency":2467,"BSSID":"30:85:a9:6c:9b:e2","SSID":"Ren_2.4G"},"ap10":{"capabilities":"[WPA2-PSK-CCMP][ESS]","level":-77,"frequency":2437,"BSSID":"00:24:36:a6:e0:13","SSID":"marjonverkko"},"ap2":{"capabilities":"[WPA2-EAP-CCMP][ESS]","level":-81,"frequency":5200,"BSSID":"24:01:c7:77:f4:7d","SSID":"eduroam"},"ap1":{"capabilities":"[WPA2-EAP-CCMP][ESS]","level":-67,"frequency":2412,"BSSID":"24:01:c7:77:f4:72","SSID":"eduroam"},"ap6":{"capabilities":"[ESS]","level":-63,"frequency":2412,"BSSID":"00:27:0d:2e:79:f1","SSID":"aalto open"},"ap5":{"capabilities":"[ESS]","level":-70,"frequency":2412,"BSSID":"24:01:c7:77:f4:71","SSID":"aalto open"},"ap4":{"capabilities":"[WPA-PSK-TKIP+CCMP][WPA2-PSK-CCMP][ESS]","level":-71,"frequency":2437,"BSSID":"c8:d3:a3:0e:cd:cc","SSID":"eMulTestBed"},"ap3":{"capabilities":"[WPA2-EAP-CCMP][ESS]","level":-81,"frequency":5320,"BSSID":"08:1f:f3:b2:d0:ad","SSID":"eduroam"}},"measurement 10":{"ap14":{"capabilities":"[WPA2-EAP-CCMP][ESS]","level":-84,"frequency":2462,"BSSID":"00:27:0d:2e:f2:82","SSID":"eduroam"},"ap15":{"capabilities":"[WPA2-EAP-CCMP][ESS]","level":-81,"frequency":2462,"BSSID":"08:1f:f3:b2:d0:a0","SSID":"aalto"},"ap12":{"capabilities":"[ESS]","level":-70,"frequency":5220,"BSSID":"00:27:0d:2e:79:fe","SSID":"aalto open"},"ap13":{"capabilities":"[WPA2-EAP-CCMP][ESS]","level":-68,"frequency":5220,"BSSID":"00:27:0d:2e:79:ff","SSID":"aalto"},"ap18":{"capabilities":"[WPA2-PSK-CCMP][ESS]","level":-94,"frequency":5540,"BSSID":"00:24:36:a6:e0:14","SSID":"marjonverkko"},"ap19":{"capabilities":"[ESS]","level":-91,"frequency":5180,"BSSID":"00:27:0d:08:c2:1e","SSID":"aalto open"},"ap16":{"capabilities":"[WPA2-EAP-CCMP][ESS]","level":-84,"frequency":2437,"BSSID":"00:27:0d:30:2a:62","SSID":"eduroam"},"ap17":{"capabilities":"[WPA2-EAP-CCMP][ESS]","level":-93,"frequency":5200,"BSSID":"00:27:0d:2e:f2:8d","SSID":"eduroam"},"ap9":{"capabilities":"[WPA2-EAP-CCMP][ESS]","level":-69,"frequency":5220,"BSSID":"00:27:0d:2e:79:fd","SSID":"eduroam"},"ap8":{"capabilities":"[ESS]","level":-82,"frequency":5320,"BSSID":"08:1f:f3:b2:d0:ae","SSID":"aalto open"},"ap7":{"capabilities":"[ESS]","level":-77,"frequency":5600,"BSSID":"d4:ca:6d:ff:31:87","SSID":"NETLEAP"},"ap11":{"capabilities":"[WPA2-PSK-CCMP][ESS]","level":-81,"frequency":2467,"BSSID":"30:85:a9:6c:9b:e2","SSID":"Ren_2.4G"},"ap10":{"capabilities":"[WPA2-PSK-CCMP][ESS]","level":-77,"frequency":2437,"BSSID":"00:24:36:a6:e0:13","SSID":"marjonverkko"},"ap2":{"capabilities":"[WPA2-EAP-CCMP][ESS]","level":-81,"frequency":5200,"BSSID":"24:01:c7:77:f4:7d","SSID":"eduroam"},"ap1":{"capabilities":"[WPA2-EAP-CCMP][ESS]","level":-67,"frequency":2412,"BSSID":"24:01:c7:77:f4:72","SSID":"eduroam"},"ap6":{"capabilities":"[ESS]","level":-63,"frequency":2412,"BSSID":"00:27:0d:2e:79:f1","SSID":"aalto open"},"ap5":{"capabilities":"[ESS]","level":-70,"frequency":2412,"BSSID":"24:01:c7:77:f4:71","SSID":"aalto open"},"ap4":{"capabilities":"[WPA-PSK-TKIP+CCMP][WPA2-PSK-CCMP][ESS]","level":-71,"frequency":2437,"BSSID":"c8:d3:a3:0e:cd:cc","SSID":"eMulTestBed"},"ap3":{"capabilities":"[WPA2-EAP-CCMP][ESS]","level":-81,"frequency":5320,"BSSID":"08:1f:f3:b2:d0:ad","SSID":"eduroam"}},"measurement 12":{"ap14":{"capabilities":"[WPA2-EAP-CCMP][ESS]","level":-81,"frequency":2462,"BSSID":"08:1f:f3:b2:d0:a0","SSID":"aalto"},"ap15":{"capabilities":"[WPA2-PSK-CCMP][ESS]","level":-92,"frequency":5540,"BSSID":"00:24:36:a6:e0:14","SSID":"marjonverkko"},"ap12":{"capabilities":"[WPA2-EAP-CCMP][ESS]","level":-76,"frequency":5220,"BSSID":"00:27:0d:2e:79:ff","SSID":"aalto"},"ap13":{"capabilities":"[WPA2-EAP-CCMP][ESS]","level":-89,"frequency":2462,"BSSID":"00:27:0d:2e:f2:82","SSID":"eduroam"},"ap18":{"capabilities":"[WPA2-PSK-CCMP][ESS]","level":-89,"frequency":5260,"BSSID":"30:85:a9:6c:9b:e4","SSID":"Ren_5G"},"ap19":{"capabilities":"[WPA2-EAP-CCMP][ESS]","level":-93,"frequency":5200,"BSSID":"00:27:0d:2e:f2:8f","SSID":"aalto"},"ap16":{"capabilities":"[WPA2-EAP-CCMP][ESS]","level":-61,"frequency":2412,"BSSID":"24:01:c7:77:f4:70","SSID":"aalto"},"ap17":{"capabilities":"[WPA2-EAP-CCMP][ESS]","level":-77,"frequency":5320,"BSSID":"08:1f:f3:b2:d0:af","SSID":"aalto"},"ap9":{"capabilities":"[WPA2-PSK-CCMP][ESS]","level":-69,"frequency":2437,"BSSID":"00:24:36:a6:e0:13","SSID":"marjonverkko"},"ap8":{"capabilities":"[WPA2-EAP-CCMP][ESS]","level":-75,"frequency":5220,"BSSID":"00:27:0d:2e:79:fd","SSID":"eduroam"},"ap7":{"capabilities":"[ESS]","level":-74,"frequency":5600,"BSSID":"d4:ca:6d:ff:31:87","SSID":"NETLEAP"},"ap20":{"capabilities":"[ESS]","level":-78,"frequency":5200,"BSSID":"24:01:c7:77:f4:7e","SSID":"aalto open"},"ap11":{"capabilities":"[ESS]","level":-79,"frequency":5220,"BSSID":"00:27:0d:2e:79:fe","SSID":"aalto open"},"ap10":{"capabilities":"[WPA2-PSK-CCMP][ESS]","level":-88,"frequency":2467,"BSSID":"30:85:a9:6c:9b:e2","SSID":"Ren_2.4G"},"ap22":{"capabilities":"[ESS]","level":-90,"frequency":2462,"BSSID":"00:27:0d:2e:f2:81","SSID":"aalto open"},"ap21":{"capabilities":"[ESS]","level":-77,"frequency":2462,"BSSID":"00:27:0d:08:c2:11","SSID":"aalto open"},"ap2":{"capabilities":"[WPA2-EAP-CCMP][ESS]","level":-73,"frequency":5200,"BSSID":"24:01:c7:77:f4:7d","SSID":"eduroam"},"ap1":{"capabilities":"[WPA2-EAP-CCMP][ESS]","level":-60,"frequency":2412,"BSSID":"24:01:c7:77:f4:72","SSID":"eduroam"},"ap6":{"capabilities":"[ESS]","level":-67,"frequency":2412,"BSSID":"00:27:0d:2e:79:f1","SSID":"aalto open"},"ap5":{"capabilities":"[ESS]","level":-59,"frequency":2412,"BSSID":"24:01:c7:77:f4:71","SSID":"aalto open"},"ap4":{"capabilities":"[WPA-PSK-TKIP+CCMP][WPA2-PSK-CCMP][ESS]","level":-69,"frequency":2437,"BSSID":"c8:d3:a3:0e:cd:cc","SSID":"eMulTestBed"},"ap3":{"capabilities":"[WPA2-EAP-CCMP][ESS]","level":-79,"frequency":5320,"BSSID":"08:1f:f3:b2:d0:ad","SSID":"eduroam"}},"measurement 11":{"ap14":{"capabilities":"[WPA2-EAP-CCMP][ESS]","level":-81,"frequency":2462,"BSSID":"08:1f:f3:b2:d0:a0","SSID":"aalto"},"ap15":{"capabilities":"[WPA2-PSK-CCMP][ESS]","level":-92,"frequency":5540,"BSSID":"00:24:36:a6:e0:14","SSID":"marjonverkko"},"ap12":{"capabilities":"[WPA2-EAP-CCMP][ESS]","level":-76,"frequency":5220,"BSSID":"00:27:0d:2e:79:ff","SSID":"aalto"},"ap13":{"capabilities":"[WPA2-EAP-CCMP][ESS]","level":-89,"frequency":2462,"BSSID":"00:27:0d:2e:f2:82","SSID":"eduroam"},"ap18":{"capabilities":"[WPA2-PSK-CCMP][ESS]","level":-89,"frequency":5260,"BSSID":"30:85:a9:6c:9b:e4","SSID":"Ren_5G"},"ap19":{"capabilities":"[WPA2-EAP-CCMP][ESS]","level":-93,"frequency":5200,"BSSID":"00:27:0d:2e:f2:8f","SSID":"aalto"},"ap16":{"capabilities":"[WPA2-EAP-CCMP][ESS]","level":-61,"frequency":2412,"BSSID":"24:01:c7:77:f4:70","SSID":"aalto"},"ap17":{"capabilities":"[WPA2-EAP-CCMP][ESS]","level":-77,"frequency":5320,"BSSID":"08:1f:f3:b2:d0:af","SSID":"aalto"},"ap9":{"capabilities":"[WPA2-PSK-CCMP][ESS]","level":-69,"frequency":2437,"BSSID":"00:24:36:a6:e0:13","SSID":"marjonverkko"},"ap8":{"capabilities":"[WPA2-EAP-CCMP][ESS]","level":-75,"frequency":5220,"BSSID":"00:27:0d:2e:79:fd","SSID":"eduroam"},"ap7":{"capabilities":"[ESS]","level":-74,"frequency":5600,"BSSID":"d4:ca:6d:ff:31:87","SSID":"NETLEAP"},"ap20":{"capabilities":"[ESS]","level":-78,"frequency":5200,"BSSID":"24:01:c7:77:f4:7e","SSID":"aalto open"},"ap11":{"capabilities":"[ESS]","level":-79,"frequency":5220,"BSSID":"00:27:0d:2e:79:fe","SSID":"aalto open"},"ap10":{"capabilities":"[WPA2-PSK-CCMP][ESS]","level":-88,"frequency":2467,"BSSID":"30:85:a9:6c:9b:e2","SSID":"Ren_2.4G"},"ap22":{"capabilities":"[ESS]","level":-90,"frequency":2462,"BSSID":"00:27:0d:2e:f2:81","SSID":"aalto open"},"ap21":{"capabilities":"[ESS]","level":-77,"frequency":2462,"BSSID":"00:27:0d:08:c2:11","SSID":"aalto open"},"ap2":{"capabilities":"[WPA2-EAP-CCMP][ESS]","level":-73,"frequency":5200,"BSSID":"24:01:c7:77:f4:7d","SSID":"eduroam"},"ap1":{"capabilities":"[WPA2-EAP-CCMP][ESS]","level":-60,"frequency":2412,"BSSID":"24:01:c7:77:f4:72","SSID":"eduroam"},"ap6":{"capabilities":"[ESS]","level":-67,"frequency":2412,"BSSID":"00:27:0d:2e:79:f1","SSID":"aalto open"},"ap5":{"capabilities":"[ESS]","level":-59,"frequency":2412,"BSSID":"24:01:c7:77:f4:71","SSID":"aalto open"},"ap4":{"capabilities":"[WPA-PSK-TKIP+CCMP][WPA2-PSK-CCMP][ESS]","level":-69,"frequency":2437,"BSSID":"c8:d3:a3:0e:cd:cc","SSID":"eMulTestBed"},"ap3":{"capabilities":"[WPA2-EAP-CCMP][ESS]","level":-79,"frequency":5320,"BSSID":"08:1f:f3:b2:d0:ad","SSID":"eduroam"}},"measurement 1":{"ap14":{"capabilities":"[WPA2-EAP-CCMP][ESS]","level":-84,"frequency":5240,"BSSID":"00:27:0d:30:2a:6f","SSID":"aalto"},"ap15":{"capabilities":"[WPA2-EAP-CCMP][ESS]","level":-80,"frequency":2412,"BSSID":"a4:56:30:e8:17:60","SSID":"aalto"},"ap12":{"capabilities":"[WPA2-EAP-CCMP][ESS]","level":-79,"frequency":2412,"BSSID":"24:01:c7:b8:d4:e2","SSID":"eduroam"},"ap13":{"capabilities":"[WPA2-EAP-CCMP][ESS]","level":-84,"frequency":5320,"BSSID":"08:1f:f3:b2:d0:af","SSID":"aalto"},"ap18":{"capabilities":"[WPA2-EAP-CCMP][ESS]","level":-83,"frequency":2412,"BSSID":"00:27:0d:08:bc:52","SSID":"eduroam"},"ap19":{"capabilities":"[WPA2-EAP-CCMP][ESS]","level":-85,"frequency":2462,"BSSID":"08:1f:f3:b2:d0:a2","SSID":"eduroam"},"ap34":{"capabilities":"[ESS]","level":-88,"frequency":5220,"BSSID":"00:27:0d:2d:dd:ce","SSID":"aalto open"},"ap16":{"capabilities":"[WPA2-EAP-CCMP][ESS]","level":-80,"frequency":2462,"BSSID":"00:27:0d:0b:d1:c2","SSID":"eduroam"},"ap35":{"capabilities":"[ESS]","level":-91,"frequency":2437,"BSSID":"a0:cf:5b:fa:34:e1","SSID":"aalto open"},"ap17":{"capabilities":"[WPA2-PSK-CCMP][ESS]","level":-82,"frequency":2437,"BSSID":"26:f7:e4:31:c2:c1","SSID":"iPhone"},"ap33":{"capabilities":"[ESS]","level":-88,"frequency":5240,"BSSID":"00:27:0d:30:2a:6e","SSID":"aalto open"},"ap32":{"capabilities":"[ESS]","level":-85,"frequency":5320,"BSSID":"08:1f:f3:b2:d0:ae","SSID":"aalto open"},"ap9":{"capabilities":"[WPA2-EAP-CCMP][ESS]","level":-81,"frequency":5200,"BSSID":"24:01:c7:77:f4:7d","SSID":"eduroam"},"ap31":{"capabilities":"[ESS]","level":-78,"frequency":2412,"BSSID":"24:01:c7:b8:d4:e1","SSID":"aalto open"},"ap8":{"capabilities":"[WPA2-EAP-CCMP][ESS]","level":-81,"frequency":5200,"BSSID":"24:01:c7:77:f4:7f","SSID":"aalto"},"ap30":{"capabilities":"[ESS]","level":-81,"frequency":5600,"BSSID":"d4:ca:6d:ff:31:87","SSID":"NETLEAP"},"ap7":{"capabilities":"[WPA2-EAP-CCMP][ESS]","level":-73,"frequency":2412,"BSSID":"00:27:0d:2e:79:f2","SSID":"eduroam"},"ap11":{"capabilities":"[WPA2-EAP-CCMP][ESS]","level":-83,"frequency":5320,"BSSID":"08:1f:f3:b2:d0:ad","SSID":"eduroam"},"ap10":{"capabilities":"[WPA2-PSK-CCMP][ESS]","level":-78,"frequency":2462,"BSSID":"a0:21:b7:9d:55:e9","SSID":"OpenWrt"},"ap2":{"capabilities":"[WPA2-EAP-CCMP][ESS]","level":-69,"frequency":2462,"BSSID":"08:1f:f3:b2:d4:b2","SSID":"eduroam"},"ap1":{"capabilities":"[WPA2-EAP-CCMP][ESS]","level":-68,"frequency":2462,"BSSID":"08:1f:f3:b2:d4:b0","SSID":"aalto"},"ap6":{"capabilities":"[WPA2-EAP-CCMP][ESS]","level":-68,"frequency":2412,"BSSID":"24:01:c7:77:f4:72","SSID":"eduroam"},"ap5":{"capabilities":"[WPA2-EAP-CCMP][ESS]","level":-66,"frequency":2437,"BSSID":"00:27:0d:30:2a:60","SSID":"aalto"},"ap4":{"capabilities":"[WPA2-EAP-CCMP][ESS]","level":-66,"frequency":2412,"BSSID":"24:01:c7:77:f4:70","SSID":"aalto"},"ap3":{"capabilities":"[WPA2-EAP-CCMP][ESS]","level":-61,"frequency":2437,"BSSID":"00:27:0d:30:2a:62","SSID":"eduroam"},"ap23":{"capabilities":"[WPA2-EAP-CCMP][ESS]","level":-89,"frequency":2412,"BSSID":"00:27:0d:08:be:82","SSID":"eduroam"},"ap24":{"capabilities":"[WPA2-EAP-CCMP][ESS]","level":-90,"frequency":2412,"BSSID":"08:1f:f3:e0:1a:40","SSID":"aalto"},"ap25":{"capabilities":"[WPA2-EAP-CCMP][ESS]","level":-90,"frequency":2412,"BSSID":"f4:4e:05:78:40:20","SSID":"aalto"},"ap26":{"capabilities":"[ESS]","level":-57,"frequency":2412,"BSSID":"24:01:c7:77:f4:71","SSID":"aalto open"},"ap27":{"capabilities":"[ESS]","level":-61,"frequency":2437,"BSSID":"00:27:0d:30:2a:61","SSID":"aalto open"},"ap28":{"capabilities":"[ESS]","level":-69,"frequency":2462,"BSSID":"08:1f:f3:b2:d4:b1","SSID":"aalto open"},"ap29":{"capabilities":"[ESS]","level":-73,"frequency":2412,"BSSID":"00:27:0d:2e:79:f1","SSID":"aalto open"},"ap20":{"capabilities":"[WPA2-EAP-CCMP][ESS]","level":-91,"frequency":5220,"BSSID":"00:27:0d:2d:dd:cd","SSID":"eduroam"},"ap22":{"capabilities":"[WPA-PSK-TKIP+CCMP][WPA2-PSK-CCMP][ESS]","level":-88,"frequency":2437,"BSSID":"c8:d3:a3:0e:cd:cc","SSID":"eMulTestBed"},"ap21":{"capabilities":"[WPA2-EAP-CCMP][ESS]","level":-87,"frequency":2437,"BSSID":"a0:cf:5b:fa:34:e0","SSID":"aalto"}},"measurement 14":{"ap14":{"capabilities":"[WPA2-EAP-CCMP][ESS]","level":-81,"frequency":2462,"BSSID":"08:1f:f3:b2:d0:a0","SSID":"aalto"},"ap15":{"capabilities":"[WPA2-PSK-CCMP][ESS]","level":-92,"frequency":5540,"BSSID":"00:24:36:a6:e0:14","SSID":"marjonverkko"},"ap12":{"capabilities":"[WPA2-EAP-CCMP][ESS]","level":-76,"frequency":5220,"BSSID":"00:27:0d:2e:79:ff","SSID":"aalto"},"ap13":{"capabilities":"[WPA2-EAP-CCMP][ESS]","level":-89,"frequency":2462,"BSSID":"00:27:0d:2e:f2:82","SSID":"eduroam"},"ap18":{"capabilities":"[WPA2-PSK-CCMP][ESS]","level":-89,"frequency":5260,"BSSID":"30:85:a9:6c:9b:e4","SSID":"Ren_5G"},"ap19":{"capabilities":"[WPA2-EAP-CCMP][ESS]","level":-93,"frequency":5200,"BSSID":"00:27:0d:2e:f2:8f","SSID":"aalto"},"ap16":{"capabilities":"[WPA2-EAP-CCMP][ESS]","level":-61,"frequency":2412,"BSSID":"24:01:c7:77:f4:70","SSID":"aalto"},"ap17":{"capabilities":"[WPA2-EAP-CCMP][ESS]","level":-77,"frequency":5320,"BSSID":"08:1f:f3:b2:d0:af","SSID":"aalto"},"ap9":{"capabilities":"[WPA2-PSK-CCMP][ESS]","level":-69,"frequency":2437,"BSSID":"00:24:36:a6:e0:13","SSID":"marjonverkko"},"ap8":{"capabilities":"[WPA2-EAP-CCMP][ESS]","level":-75,"frequency":5220,"BSSID":"00:27:0d:2e:79:fd","SSID":"eduroam"},"ap7":{"capabilities":"[ESS]","level":-74,"frequency":5600,"BSSID":"d4:ca:6d:ff:31:87","SSID":"NETLEAP"},"ap20":{"capabilities":"[ESS]","level":-78,"frequency":5200,"BSSID":"24:01:c7:77:f4:7e","SSID":"aalto open"},"ap11":{"capabilities":"[ESS]","level":-79,"frequency":5220,"BSSID":"00:27:0d:2e:79:fe","SSID":"aalto open"},"ap10":{"capabilities":"[WPA2-PSK-CCMP][ESS]","level":-88,"frequency":2467,"BSSID":"30:85:a9:6c:9b:e2","SSID":"Ren_2.4G"},"ap22":{"capabilities":"[ESS]","level":-90,"frequency":2462,"BSSID":"00:27:0d:2e:f2:81","SSID":"aalto open"},"ap21":{"capabilities":"[ESS]","level":-77,"frequency":2462,"BSSID":"00:27:0d:08:c2:11","SSID":"aalto open"},"ap2":{"capabilities":"[WPA2-EAP-CCMP][ESS]","level":-73,"frequency":5200,"BSSID":"24:01:c7:77:f4:7d","SSID":"eduroam"},"ap1":{"capabilities":"[WPA2-EAP-CCMP][ESS]","level":-60,"frequency":2412,"BSSID":"24:01:c7:77:f4:72","SSID":"eduroam"},"ap6":{"capabilities":"[ESS]","level":-67,"frequency":2412,"BSSID":"00:27:0d:2e:79:f1","SSID":"aalto open"},"ap5":{"capabilities":"[ESS]","level":-59,"frequency":2412,"BSSID":"24:01:c7:77:f4:71","SSID":"aalto open"},"ap4":{"capabilities":"[WPA-PSK-TKIP+CCMP][WPA2-PSK-CCMP][ESS]","level":-69,"frequency":2437,"BSSID":"c8:d3:a3:0e:cd:cc","SSID":"eMulTestBed"},"ap3":{"capabilities":"[WPA2-EAP-CCMP][ESS]","level":-79,"frequency":5320,"BSSID":"08:1f:f3:b2:d0:ad","SSID":"eduroam"}},"measurement 2":{"ap14":{"capabilities":"[WPA2-EAP-CCMP][ESS]","level":-84,"frequency":5240,"BSSID":"00:27:0d:30:2a:6f","SSID":"aalto"},"ap15":{"capabilities":"[WPA2-EAP-CCMP][ESS]","level":-80,"frequency":2412,"BSSID":"a4:56:30:e8:17:60","SSID":"aalto"},"ap12":{"capabilities":"[WPA2-EAP-CCMP][ESS]","level":-79,"frequency":2412,"BSSID":"24:01:c7:b8:d4:e2","SSID":"eduroam"},"ap13":{"capabilities":"[WPA2-EAP-CCMP][ESS]","level":-84,"frequency":5320,"BSSID":"08:1f:f3:b2:d0:af","SSID":"aalto"},"ap18":{"capabilities":"[WPA2-EAP-CCMP][ESS]","level":-83,"frequency":2412,"BSSID":"00:27:0d:08:bc:52","SSID":"eduroam"},"ap19":{"capabilities":"[WPA2-EAP-CCMP][ESS]","level":-85,"frequency":2462,"BSSID":"08:1f:f3:b2:d0:a2","SSID":"eduroam"},"ap34":{"capabilities":"[ESS]","level":-88,"frequency":5220,"BSSID":"00:27:0d:2d:dd:ce","SSID":"aalto open"},"ap16":{"capabilities":"[WPA2-EAP-CCMP][ESS]","level":-80,"frequency":2462,"BSSID":"00:27:0d:0b:d1:c2","SSID":"eduroam"},"ap35":{"capabilities":"[ESS]","level":-91,"frequency":2437,"BSSID":"a0:cf:5b:fa:34:e1","SSID":"aalto open"},"ap17":{"capabilities":"[WPA2-PSK-CCMP][ESS]","level":-82,"frequency":2437,"BSSID":"26:f7:e4:31:c2:c1","SSID":"iPhone"},"ap33":{"capabilities":"[ESS]","level":-88,"frequency":5240,"BSSID":"00:27:0d:30:2a:6e","SSID":"aalto open"},"ap32":{"capabilities":"[ESS]","level":-85,"frequency":5320,"BSSID":"08:1f:f3:b2:d0:ae","SSID":"aalto open"},"ap9":{"capabilities":"[WPA2-EAP-CCMP][ESS]","level":-81,"frequency":5200,"BSSID":"24:01:c7:77:f4:7d","SSID":"eduroam"},"ap31":{"capabilities":"[ESS]","level":-78,"frequency":2412,"BSSID":"24:01:c7:b8:d4:e1","SSID":"aalto open"},"ap8":{"capabilities":"[WPA2-EAP-CCMP][ESS]","level":-81,"frequency":5200,"BSSID":"24:01:c7:77:f4:7f","SSID":"aalto"},"ap30":{"capabilities":"[ESS]","level":-81,"frequency":5600,"BSSID":"d4:ca:6d:ff:31:87","SSID":"NETLEAP"},"ap7":{"capabilities":"[WPA2-EAP-CCMP][ESS]","level":-73,"frequency":2412,"BSSID":"00:27:0d:2e:79:f2","SSID":"eduroam"},"ap11":{"capabilities":"[WPA2-EAP-CCMP][ESS]","level":-83,"frequency":5320,"BSSID":"08:1f:f3:b2:d0:ad","SSID":"eduroam"},"ap10":{"capabilities":"[WPA2-PSK-CCMP][ESS]","level":-78,"frequency":2462,"BSSID":"a0:21:b7:9d:55:e9","SSID":"OpenWrt"},"ap2":{"capabilities":"[WPA2-EAP-CCMP][ESS]","level":-69,"frequency":2462,"BSSID":"08:1f:f3:b2:d4:b2","SSID":"eduroam"},"ap1":{"capabilities":"[WPA2-EAP-CCMP][ESS]","level":-68,"frequency":2462,"BSSID":"08:1f:f3:b2:d4:b0","SSID":"aalto"},"ap6":{"capabilities":"[WPA2-EAP-CCMP][ESS]","level":-68,"frequency":2412,"BSSID":"24:01:c7:77:f4:72","SSID":"eduroam"},"ap5":{"capabilities":"[WPA2-EAP-CCMP][ESS]","level":-66,"frequency":2437,"BSSID":"00:27:0d:30:2a:60","SSID":"aalto"},"ap4":{"capabilities":"[WPA2-EAP-CCMP][ESS]","level":-66,"frequency":2412,"BSSID":"24:01:c7:77:f4:70","SSID":"aalto"},"ap3":{"capabilities":"[WPA2-EAP-CCMP][ESS]","level":-61,"frequency":2437,"BSSID":"00:27:0d:30:2a:62","SSID":"eduroam"},"ap23":{"capabilities":"[WPA2-EAP-CCMP][ESS]","level":-89,"frequency":2412,"BSSID":"00:27:0d:08:be:82","SSID":"eduroam"},"ap24":{"capabilities":"[WPA2-EAP-CCMP][ESS]","level":-90,"frequency":2412,"BSSID":"08:1f:f3:e0:1a:40","SSID":"aalto"},"ap25":{"capabilities":"[WPA2-EAP-CCMP][ESS]","level":-90,"frequency":2412,"BSSID":"f4:4e:05:78:40:20","SSID":"aalto"},"ap26":{"capabilities":"[ESS]","level":-57,"frequency":2412,"BSSID":"24:01:c7:77:f4:71","SSID":"aalto open"},"ap27":{"capabilities":"[ESS]","level":-61,"frequency":2437,"BSSID":"00:27:0d:30:2a:61","SSID":"aalto open"},"ap28":{"capabilities":"[ESS]","level":-69,"frequency":2462,"BSSID":"08:1f:f3:b2:d4:b1","SSID":"aalto open"},"ap29":{"capabilities":"[ESS]","level":-73,"frequency":2412,"BSSID":"00:27:0d:2e:79:f1","SSID":"aalto open"},"ap20":{"capabilities":"[WPA2-EAP-CCMP][ESS]","level":-91,"frequency":5220,"BSSID":"00:27:0d:2d:dd:cd","SSID":"eduroam"},"ap22":{"capabilities":"[WPA-PSK-TKIP+CCMP][WPA2-PSK-CCMP][ESS]","level":-88,"frequency":2437,"BSSID":"c8:d3:a3:0e:cd:cc","SSID":"eMulTestBed"},"ap21":{"capabilities":"[WPA2-EAP-CCMP][ESS]","level":-87,"frequency":2437,"BSSID":"a0:cf:5b:fa:34:e0","SSID":"aalto"}},"measurement 13":{"ap14":{"capabilities":"[WPA2-EAP-CCMP][ESS]","level":-81,"frequency":2462,"BSSID":"08:1f:f3:b2:d0:a0","SSID":"aalto"},"ap15":{"capabilities":"[WPA2-PSK-CCMP][ESS]","level":-92,"frequency":5540,"BSSID":"00:24:36:a6:e0:14","SSID":"marjonverkko"},"ap12":{"capabilities":"[WPA2-EAP-CCMP][ESS]","level":-76,"frequency":5220,"BSSID":"00:27:0d:2e:79:ff","SSID":"aalto"},"ap13":{"capabilities":"[WPA2-EAP-CCMP][ESS]","level":-89,"frequency":2462,"BSSID":"00:27:0d:2e:f2:82","SSID":"eduroam"},"ap18":{"capabilities":"[WPA2-PSK-CCMP][ESS]","level":-89,"frequency":5260,"BSSID":"30:85:a9:6c:9b:e4","SSID":"Ren_5G"},"ap19":{"capabilities":"[WPA2-EAP-CCMP][ESS]","level":-93,"frequency":5200,"BSSID":"00:27:0d:2e:f2:8f","SSID":"aalto"},"ap16":{"capabilities":"[WPA2-EAP-CCMP][ESS]","level":-61,"frequency":2412,"BSSID":"24:01:c7:77:f4:70","SSID":"aalto"},"ap17":{"capabilities":"[WPA2-EAP-CCMP][ESS]","level":-77,"frequency":5320,"BSSID":"08:1f:f3:b2:d0:af","SSID":"aalto"},"ap9":{"capabilities":"[WPA2-PSK-CCMP][ESS]","level":-69,"frequency":2437,"BSSID":"00:24:36:a6:e0:13","SSID":"marjonverkko"},"ap8":{"capabilities":"[WPA2-EAP-CCMP][ESS]","level":-75,"frequency":5220,"BSSID":"00:27:0d:2e:79:fd","SSID":"eduroam"},"ap7":{"capabilities":"[ESS]","level":-74,"frequency":5600,"BSSID":"d4:ca:6d:ff:31:87","SSID":"NETLEAP"},"ap20":{"capabilities":"[ESS]","level":-78,"frequency":5200,"BSSID":"24:01:c7:77:f4:7e","SSID":"aalto open"},"ap11":{"capabilities":"[ESS]","level":-79,"frequency":5220,"BSSID":"00:27:0d:2e:79:fe","SSID":"aalto open"},"ap10":{"capabilities":"[WPA2-PSK-CCMP][ESS]","level":-88,"frequency":2467,"BSSID":"30:85:a9:6c:9b:e2","SSID":"Ren_2.4G"},"ap22":{"capabilities":"[ESS]","level":-90,"frequency":2462,"BSSID":"00:27:0d:2e:f2:81","SSID":"aalto open"},"ap21":{"capabilities":"[ESS]","level":-77,"frequency":2462,"BSSID":"00:27:0d:08:c2:11","SSID":"aalto open"},"ap2":{"capabilities":"[WPA2-EAP-CCMP][ESS]","level":-73,"frequency":5200,"BSSID":"24:01:c7:77:f4:7d","SSID":"eduroam"},"ap1":{"capabilities":"[WPA2-EAP-CCMP][ESS]","level":-60,"frequency":2412,"BSSID":"24:01:c7:77:f4:72","SSID":"eduroam"},"ap6":{"capabilities":"[ESS]","level":-67,"frequency":2412,"BSSID":"00:27:0d:2e:79:f1","SSID":"aalto open"},"ap5":{"capabilities":"[ESS]","level":-59,"frequency":2412,"BSSID":"24:01:c7:77:f4:71","SSID":"aalto open"},"ap4":{"capabilities":"[WPA-PSK-TKIP+CCMP][WPA2-PSK-CCMP][ESS]","level":-69,"frequency":2437,"BSSID":"c8:d3:a3:0e:cd:cc","SSID":"eMulTestBed"},"ap3":{"capabilities":"[WPA2-EAP-CCMP][ESS]","level":-79,"frequency":5320,"BSSID":"08:1f:f3:b2:d0:ad","SSID":"eduroam"}},"measurement 3":{"ap14":{"capabilities":"[WPA2-EAP-CCMP][ESS]","level":-84,"frequency":5240,"BSSID":"00:27:0d:30:2a:6f","SSID":"aalto"},"ap15":{"capabilities":"[WPA2-EAP-CCMP][ESS]","level":-80,"frequency":2412,"BSSID":"a4:56:30:e8:17:60","SSID":"aalto"},"ap12":{"capabilities":"[WPA2-EAP-CCMP][ESS]","level":-79,"frequency":2412,"BSSID":"24:01:c7:b8:d4:e2","SSID":"eduroam"},"ap13":{"capabilities":"[WPA2-EAP-CCMP][ESS]","level":-84,"frequency":5320,"BSSID":"08:1f:f3:b2:d0:af","SSID":"aalto"},"ap18":{"capabilities":"[WPA2-EAP-CCMP][ESS]","level":-83,"frequency":2412,"BSSID":"00:27:0d:08:bc:52","SSID":"eduroam"},"ap19":{"capabilities":"[WPA2-EAP-CCMP][ESS]","level":-85,"frequency":2462,"BSSID":"08:1f:f3:b2:d0:a2","SSID":"eduroam"},"ap34":{"capabilities":"[ESS]","level":-88,"frequency":5220,"BSSID":"00:27:0d:2d:dd:ce","SSID":"aalto open"},"ap16":{"capabilities":"[WPA2-EAP-CCMP][ESS]","level":-80,"frequency":2462,"BSSID":"00:27:0d:0b:d1:c2","SSID":"eduroam"},"ap35":{"capabilities":"[ESS]","level":-91,"frequency":2437,"BSSID":"a0:cf:5b:fa:34:e1","SSID":"aalto open"},"ap17":{"capabilities":"[WPA2-PSK-CCMP][ESS]","level":-82,"frequency":2437,"BSSID":"26:f7:e4:31:c2:c1","SSID":"iPhone"},"ap33":{"capabilities":"[ESS]","level":-88,"frequency":5240,"BSSID":"00:27:0d:30:2a:6e","SSID":"aalto open"},"ap32":{"capabilities":"[ESS]","level":-85,"frequency":5320,"BSSID":"08:1f:f3:b2:d0:ae","SSID":"aalto open"},"ap9":{"capabilities":"[WPA2-EAP-CCMP][ESS]","level":-81,"frequency":5200,"BSSID":"24:01:c7:77:f4:7d","SSID":"eduroam"},"ap31":{"capabilities":"[ESS]","level":-78,"frequency":2412,"BSSID":"24:01:c7:b8:d4:e1","SSID":"aalto open"},"ap8":{"capabilities":"[WPA2-EAP-CCMP][ESS]","level":-81,"frequency":5200,"BSSID":"24:01:c7:77:f4:7f","SSID":"aalto"},"ap30":{"capabilities":"[ESS]","level":-81,"frequency":5600,"BSSID":"d4:ca:6d:ff:31:87","SSID":"NETLEAP"},"ap7":{"capabilities":"[WPA2-EAP-CCMP][ESS]","level":-73,"frequency":2412,"BSSID":"00:27:0d:2e:79:f2","SSID":"eduroam"},"ap11":{"capabilities":"[WPA2-EAP-CCMP][ESS]","level":-83,"frequency":5320,"BSSID":"08:1f:f3:b2:d0:ad","SSID":"eduroam"},"ap10":{"capabilities":"[WPA2-PSK-CCMP][ESS]","level":-78,"frequency":2462,"BSSID":"a0:21:b7:9d:55:e9","SSID":"OpenWrt"},"ap2":{"capabilities":"[WPA2-EAP-CCMP][ESS]","level":-69,"frequency":2462,"BSSID":"08:1f:f3:b2:d4:b2","SSID":"eduroam"},"ap1":{"capabilities":"[WPA2-EAP-CCMP][ESS]","level":-68,"frequency":2462,"BSSID":"08:1f:f3:b2:d4:b0","SSID":"aalto"},"ap6":{"capabilities":"[WPA2-EAP-CCMP][ESS]","level":-68,"frequency":2412,"BSSID":"24:01:c7:77:f4:72","SSID":"eduroam"},"ap5":{"capabilities":"[WPA2-EAP-CCMP][ESS]","level":-66,"frequency":2437,"BSSID":"00:27:0d:30:2a:60","SSID":"aalto"},"ap4":{"capabilities":"[WPA2-EAP-CCMP][ESS]","level":-66,"frequency":2412,"BSSID":"24:01:c7:77:f4:70","SSID":"aalto"},"ap3":{"capabilities":"[WPA2-EAP-CCMP][ESS]","level":-61,"frequency":2437,"BSSID":"00:27:0d:30:2a:62","SSID":"eduroam"},"ap23":{"capabilities":"[WPA2-EAP-CCMP][ESS]","level":-89,"frequency":2412,"BSSID":"00:27:0d:08:be:82","SSID":"eduroam"},"ap24":{"capabilities":"[WPA2-EAP-CCMP][ESS]","level":-90,"frequency":2412,"BSSID":"08:1f:f3:e0:1a:40","SSID":"aalto"},"ap25":{"capabilities":"[WPA2-EAP-CCMP][ESS]","level":-90,"frequency":2412,"BSSID":"f4:4e:05:78:40:20","SSID":"aalto"},"ap26":{"capabilities":"[ESS]","level":-57,"frequency":2412,"BSSID":"24:01:c7:77:f4:71","SSID":"aalto open"},"ap27":{"capabilities":"[ESS]","level":-61,"frequency":2437,"BSSID":"00:27:0d:30:2a:61","SSID":"aalto open"},"ap28":{"capabilities":"[ESS]","level":-69,"frequency":2462,"BSSID":"08:1f:f3:b2:d4:b1","SSID":"aalto open"},"ap29":{"capabilities":"[ESS]","level":-73,"frequency":2412,"BSSID":"00:27:0d:2e:79:f1","SSID":"aalto open"},"ap20":{"capabilities":"[WPA2-EAP-CCMP][ESS]","level":-91,"frequency":5220,"BSSID":"00:27:0d:2d:dd:cd","SSID":"eduroam"},"ap22":{"capabilities":"[WPA-PSK-TKIP+CCMP][WPA2-PSK-CCMP][ESS]","level":-88,"frequency":2437,"BSSID":"c8:d3:a3:0e:cd:cc","SSID":"eMulTestBed"},"ap21":{"capabilities":"[WPA2-EAP-CCMP][ESS]","level":-87,"frequency":2437,"BSSID":"a0:cf:5b:fa:34:e0","SSID":"aalto"}},"measurement 15":{"ap14":{"capabilities":"[WPA2-EAP-CCMP][ESS]","level":-81,"frequency":2462,"BSSID":"08:1f:f3:b2:d0:a0","SSID":"aalto"},"ap15":{"capabilities":"[WPA2-PSK-CCMP][ESS]","level":-92,"frequency":5540,"BSSID":"00:24:36:a6:e0:14","SSID":"marjonverkko"},"ap12":{"capabilities":"[WPA2-EAP-CCMP][ESS]","level":-76,"frequency":5220,"BSSID":"00:27:0d:2e:79:ff","SSID":"aalto"},"ap13":{"capabilities":"[WPA2-EAP-CCMP][ESS]","level":-89,"frequency":2462,"BSSID":"00:27:0d:2e:f2:82","SSID":"eduroam"},"ap18":{"capabilities":"[WPA2-PSK-CCMP][ESS]","level":-89,"frequency":5260,"BSSID":"30:85:a9:6c:9b:e4","SSID":"Ren_5G"},"ap19":{"capabilities":"[WPA2-EAP-CCMP][ESS]","level":-93,"frequency":5200,"BSSID":"00:27:0d:2e:f2:8f","SSID":"aalto"},"ap16":{"capabilities":"[WPA2-EAP-CCMP][ESS]","level":-61,"frequency":2412,"BSSID":"24:01:c7:77:f4:70","SSID":"aalto"},"ap17":{"capabilities":"[WPA2-EAP-CCMP][ESS]","level":-77,"frequency":5320,"BSSID":"08:1f:f3:b2:d0:af","SSID":"aalto"},"ap9":{"capabilities":"[WPA2-PSK-CCMP][ESS]","level":-69,"frequency":2437,"BSSID":"00:24:36:a6:e0:13","SSID":"marjonverkko"},"ap8":{"capabilities":"[WPA2-EAP-CCMP][ESS]","level":-75,"frequency":5220,"BSSID":"00:27:0d:2e:79:fd","SSID":"eduroam"},"ap7":{"capabilities":"[ESS]","level":-74,"frequency":5600,"BSSID":"d4:ca:6d:ff:31:87","SSID":"NETLEAP"},"ap20":{"capabilities":"[ESS]","level":-78,"frequency":5200,"BSSID":"24:01:c7:77:f4:7e","SSID":"aalto open"},"ap11":{"capabilities":"[ESS]","level":-79,"frequency":5220,"BSSID":"00:27:0d:2e:79:fe","SSID":"aalto open"},"ap10":{"capabilities":"[WPA2-PSK-CCMP][ESS]","level":-88,"frequency":2467,"BSSID":"30:85:a9:6c:9b:e2","SSID":"Ren_2.4G"},"ap22":{"capabilities":"[ESS]","level":-90,"frequency":2462,"BSSID":"00:27:0d:2e:f2:81","SSID":"aalto open"},"ap21":{"capabilities":"[ESS]","level":-77,"frequency":2462,"BSSID":"00:27:0d:08:c2:11","SSID":"aalto open"},"ap2":{"capabilities":"[WPA2-EAP-CCMP][ESS]","level":-73,"frequency":5200,"BSSID":"24:01:c7:77:f4:7d","SSID":"eduroam"},"ap1":{"capabilities":"[WPA2-EAP-CCMP][ESS]","level":-60,"frequency":2412,"BSSID":"24:01:c7:77:f4:72","SSID":"eduroam"},"ap6":{"capabilities":"[ESS]","level":-67,"frequency":2412,"BSSID":"00:27:0d:2e:79:f1","SSID":"aalto open"},"ap5":{"capabilities":"[ESS]","level":-59,"frequency":2412,"BSSID":"24:01:c7:77:f4:71","SSID":"aalto open"},"ap4":{"capabilities":"[WPA-PSK-TKIP+CCMP][WPA2-PSK-CCMP][ESS]","level":-69,"frequency":2437,"BSSID":"c8:d3:a3:0e:cd:cc","SSID":"eMulTestBed"},"ap3":{"capabilities":"[WPA2-EAP-CCMP][ESS]","level":-79,"frequency":5320,"BSSID":"08:1f:f3:b2:d0:ad","SSID":"eduroam"}}}